apiazure/__init__.py
apiazure/apiazure.py
azure_api_ccastillo1-0.0.1.dist-info/METADATA
azure_api_ccastillo1-0.0.1.dist-info/WHEEL
azure_api_ccastillo1-0.0.1.dist-info/top_level.txt
azure_api_ccastillo1-0.0.1.dist-info/RECORD
