Metadata-Version: 2.1
Name: azure_api_ccastillo1
Version: 0.0.1
Summary: Libreria para el uso de la api de azure devops
Author-email: Carlos Castillo <robocarlos10@gmail.com>
Classifier: Programming Language :: Python :: 3
Requires-Python: >=3.12
